savef.py
savef-0.3.dist-info/WHEEL
savef-0.3.dist-info/METADATA
savef-0.3.dist-info/RECORD
