Metadata-Version: 1.2
Name: savef
Version: 0.3
Summary: Save last line to a file specified , builds python script as a stack of commands
Home-page: https://github.com/vegabondx/savef
License: UNKNOWN
Author: Abhijit Oka
Author-email: abhijit.oka@hotmail.com
Classifier: License :: OSI Approved :: MIT License
Requires-Dist: ipython
